hbllmutils/__init__.py
hbllmutils/config/__init__.py
hbllmutils/config/meta.py
hbllmutils/history/__init__.py
hbllmutils/history/history.py
hbllmutils/history/image.py
hbllmutils/manage/__init__.py
hbllmutils/manage/config.py
hbllmutils/meta/__init__.py
hbllmutils/meta/datamodel/__init__.py
hbllmutils/meta/datamodel/dataclass-simple-withc.prompt.txt
hbllmutils/meta/datamodel/dataclass-simple-withc.py.txt
hbllmutils/meta/datamodel/dataclass-simple.prompt.txt
hbllmutils/meta/datamodel/dataclass-simple.py.txt
hbllmutils/meta/datamodel/prompt.j2
hbllmutils/meta/datamodel/prompt.py
hbllmutils/meta/datamodel/pydantic-main.prompt.txt
hbllmutils/meta/datamodel/pydantic-main.py.txt
hbllmutils/meta/datamodel/pydantic-or.prompt.txt
hbllmutils/meta/datamodel/pydantic-or.py.txt
hbllmutils/meta/datamodel/sample.py
hbllmutils/meta/datamodel/task.py
hbllmutils/model/__init__.py
hbllmutils/model/base.py
hbllmutils/model/fake.py
hbllmutils/model/load.py
hbllmutils/model/remote.py
hbllmutils/model/stream.py
hbllmutils/model/task.py
hbllmutils/response/__init__.py
hbllmutils/response/code.py
hbllmutils/response/datamodel.py
hbllmutils/response/parsable.py
hbllmutils/template/__init__.py
hbllmutils/template/decode.py
hbllmutils/template/env.py
hbllmutils/template/matcher.py
hbllmutils/template/matcher_pair.py
hbllmutils/template/render.py
hbllmutils/testing/__init__.py
hbllmutils/testing/alive.py
hbllmutils/testing/base.py
hbllmutils/utils/__init__.py
hbllmutils/utils/logging.py
hbllmutils/utils/truncate.py
hbllmutils-0.3.1.dist-info/LICENSE
hbllmutils-0.3.1.dist-info/METADATA
hbllmutils-0.3.1.dist-info/WHEEL
hbllmutils-0.3.1.dist-info/top_level.txt
hbllmutils-0.3.1.dist-info/RECORD
