Metadata-Version: 2.1
Name: hbllmutils
Version: 0.3.1
Summary: A Python utility library for streamlined Large Language Model interactions with unified API and conversation management.
Home-page: https://github.com/HansBug/hbllmutils
Author: HansBug
Author-email: hansbug@buaa.edu.cn
License: Apache License, Version 2.0
Project-URL: Homepage, https://github.com/HansBug/hbllmutils
Project-URL: Documentation, https://hbllmutils.readthedocs.io/en/latest/
Project-URL: Repository, https://github.com/HansBug/hbllmutils
Project-URL: Bug Reports, https://github.com/HansBug/hbllmutils/issues
Project-URL: Source, https://github.com/HansBug/hbllmutils
Keywords: llm,large language models,openai,api,chatbot,ai,machine learning,nlp,natural language processing,conversation,streaming,async,configuration management,deepseek,gpt,claude,gemini
Classifier: Development Status :: 4 - Beta
Classifier: Intended Audience :: Developers
Classifier: Intended Audience :: Information Technology
Classifier: Intended Audience :: Science/Research
Classifier: Intended Audience :: Education
Classifier: License :: OSI Approved :: Apache Software License
Classifier: Operating System :: OS Independent
Classifier: Operating System :: POSIX
Classifier: Operating System :: POSIX :: Linux
Classifier: Operating System :: Microsoft :: Windows
Classifier: Operating System :: MacOS
Classifier: Programming Language :: Python
Classifier: Programming Language :: Python :: 3
Classifier: Programming Language :: Python :: 3 :: Only
Classifier: Programming Language :: Python :: 3.7
Classifier: Programming Language :: Python :: 3.8
Classifier: Programming Language :: Python :: 3.9
Classifier: Programming Language :: Python :: 3.10
Classifier: Programming Language :: Python :: 3.11
Classifier: Programming Language :: Python :: 3.12
Classifier: Programming Language :: Python :: 3.13
Classifier: Programming Language :: Python :: 3.14
Classifier: Programming Language :: Python :: Implementation :: CPython
Classifier: Programming Language :: Python :: Implementation :: PyPy
Classifier: Topic :: Software Development
Classifier: Topic :: Software Development :: Libraries
Classifier: Topic :: Software Development :: Libraries :: Python Modules
Classifier: Topic :: Scientific/Engineering
Classifier: Topic :: Scientific/Engineering :: Artificial Intelligence
Classifier: Topic :: Text Processing
Classifier: Topic :: Text Processing :: Linguistic
Classifier: Topic :: Communications :: Chat
Classifier: Topic :: Internet :: WWW/HTTP :: Dynamic Content
Classifier: Topic :: Utilities
Classifier: Natural Language :: English
Classifier: Environment :: Console
Classifier: Environment :: Web Environment
Classifier: Typing :: Typed
Requires-Python: >=3.7
License-File: LICENSE
Requires-Dist: hbutils >=0.14.2
Requires-Dist: openai
Requires-Dist: tqdm
Requires-Dist: pillow
Requires-Dist: numpy
Requires-Dist: pyyaml
Requires-Dist: jieba
Requires-Dist: markdown-it-py
Requires-Dist: json-repair
Requires-Dist: pydantic
Requires-Dist: jinja2
Requires-Dist: natsort
Provides-Extra: dev
Requires-Dist: openai ; extra == 'dev'
Requires-Dist: ruff ; extra == 'dev'
Requires-Dist: sphinx >=3.2.0 ; extra == 'dev'
Requires-Dist: natsort ; extra == 'dev'
Provides-Extra: doc
Requires-Dist: Jinja2 >=3.0.0 ; extra == 'doc'
Requires-Dist: sphinx >=3.2.0 ; extra == 'doc'
Requires-Dist: sphinx-rtd-theme >=0.4.3 ; extra == 'doc'
Requires-Dist: enum-tools >=0.9.0 ; extra == 'doc'
Requires-Dist: sphinx-toolbox ; extra == 'doc'
Requires-Dist: plantumlcli >=0.0.2 ; extra == 'doc'
Requires-Dist: packaging ; extra == 'doc'
Requires-Dist: sphinx-multiversion >=0.2.4 ; extra == 'doc'
Requires-Dist: where >=1.0.2 ; extra == 'doc'
Requires-Dist: easydict <2,>=1.7 ; extra == 'doc'
Requires-Dist: natsort ; extra == 'doc'
Provides-Extra: test
Requires-Dist: coverage >=5 ; extra == 'test'
Requires-Dist: mock >=4.0.3 ; extra == 'test'
Requires-Dist: flake8 >=3.5 ; extra == 'test'
Requires-Dist: pytest >=6.2.5 ; extra == 'test'
Requires-Dist: pytest-cov >=3.0.0 ; extra == 'test'
Requires-Dist: pytest-mock >=3.6.1 ; extra == 'test'
Requires-Dist: pytest-xdist >=1.34.0 ; extra == 'test'
Requires-Dist: pytest-rerunfailures >=10.2 ; extra == 'test'
Requires-Dist: pytest-timeout >=2.0.2 ; extra == 'test'
Requires-Dist: easydict <2,>=1.7 ; extra == 'test'
